[
  {
    "name": "Agro Pineapple V2",
    "description": {
      "en": "Sweet pineapple grown with natural compost.",
      "fr": "Ananas sucré cultivé avec du compost naturel."
    },
    "category": "Fruits",
    "certification": "Certified Organic",
    "nutritionalBenefits": ["Vitamin C", "Hydration"],
    "image": "https://images.unsplash.com/photo-pineapple"
  },
  {
    "name": "Herbal Kale Plus",
    "description": {
      "en": "Kale leaves rich in antioxidants and fiber.",
      "fr": "Feuilles de chou riches en antioxydants et en fibres."
    },
    "category": "Vegetables",
    "certification": "In Conversion",
    "nutritionalBenefits": ["Antioxidants", "Vitamin K"],
    "image": "https://images.unsplash.com/photo-kale"
  }
]
